ideogram_wrapper/__init__.py
ideogram_wrapper-0.0.2.dist-info/METADATA
ideogram_wrapper-0.0.2.dist-info/WHEEL
ideogram_wrapper-0.0.2.dist-info/top_level.txt
ideogram_wrapper-0.0.2.dist-info/RECORD
